README.md
setup.py
boxflow/__init__.py
boxflow/command.py
boxflow/dataflow.py
boxflow/server.py
boxflow.egg-info/PKG-INFO
boxflow.egg-info/SOURCES.txt
boxflow.egg-info/dependency_links.txt
boxflow.egg-info/entry_points.txt
boxflow.egg-info/requires.txt
boxflow.egg-info/top_level.txt
boxflow/assets/example.png
boxflow/assets/manhattan.png
boxflow/interface/__init__.py
boxflow/interface/holoviews.py
boxflow/interface/imagen.py
boxflow/interface/inventory.py
boxflow/interface/numbergen.py
boxflow/interface/param.py
boxflow/interface/paramDatGUI.py
boxflow/js/boxes.js
boxflow/js/commlink.js
boxflow/js/connector.js
boxflow/js/graph.js
boxflow/js/gui.js
boxflow/js/main.js
boxflow/js/nodes.js
boxflow/js/tools.js
boxflow/js/utils.js
boxflow/js/view.js
boxflow/static/dat.gui.js
boxflow/static/fabric.js
boxflow/static/jquery.min.js
boxflow/static/underscore-min.js
boxflow/static/watch.js