Metadata-Version: 2.1
Name: boxflow
Version: 0.0.4
Summary: Visual dataflow programming between parameterized objects.
Home-page: https://github.com/ioam/boxflow
Author: Jean-Luc Stevens
Author-email: jlrstevens@gmail.com
Maintainer: IOAM
Maintainer-email: jlrstevens@gmail.com
License: BSD
Platform: Windows
Platform: Mac OS X
Platform: Linux
Classifier: License :: OSI Approved :: BSD License
Classifier: Development Status :: 3 - Alpha
Classifier: Programming Language :: Python :: 2.7
Classifier: Programming Language :: Python :: 3.3
Classifier: Programming Language :: Python :: 3.4
Classifier: Programming Language :: Python :: 3.5
Classifier: Programming Language :: Python :: 3.6
Classifier: Operating System :: OS Independent
Classifier: Intended Audience :: Science/Research
Classifier: Intended Audience :: Developers
Classifier: Natural Language :: English
Classifier: Topic :: Scientific/Engineering
Classifier: Topic :: Software Development :: Libraries
Provides-Extra: all
